dpay_lib-0.1.5.dist-info/METADATA
dpay_lib-0.1.5.dist-info/RECORD
dpay_lib-0.1.5.dist-info/WHEEL
dpay_lib-0.1.5.dist-info/top_level.txt
dpaypy/__init__.py
dpaypy/account.py
dpaypy/aes.py
dpaypy/amount.py
dpaypy/block.py
dpaypy/blockchain.py
dpaypy/blog.py
dpaypy/converter.py
dpaypy/data.py
dpaypy/dex.py
dpaypy/dpay.py
dpaypy/exceptions.py
dpaypy/instance.py
dpaypy/post.py
dpaypy/profile.py
dpaypy/savings.py
dpaypy/storage.py
dpaypy/transactionbuilder.py
dpaypy/utils.py
dpaypy/wallet.py
dpaypy/witness.py
dpaypyapi/__init__.py
dpaypyapi/dpayasyncclient.py
dpaypyapi/dpayclient.py
dpaypyapi/dpaynoderpc.py
dpaypyapi/dpaywalletrpc.py
dpaypyapi/exceptions.py
dpaypybase/__init__.py
dpaypybase/account.py
dpaypybase/chains.py
dpaypybase/memo.py
dpaypybase/objecttypes.py
dpaypybase/operationids.py
dpaypybase/operations.py
dpaypybase/signedtransactions.py
dpaypybase/transactions.py
